daisyfontconverter/__init__.py
daisyfontconverter/cli.py
daisyfontconverter-1.0.0.dist-info/LICENSE
daisyfontconverter-1.0.0.dist-info/METADATA
daisyfontconverter-1.0.0.dist-info/WHEEL
daisyfontconverter-1.0.0.dist-info/entry_points.txt
daisyfontconverter-1.0.0.dist-info/RECORD
