Metadata-Version: 2.1
Name: daisyfontconverter
Version: 1.0.0
Summary: A small command line tool to convert PixelForge font files into c-arrays for the electrosmith daisy
Author: atoav
Author-email: dh@atoav.com
Requires-Python: >=3.10,<4.0
Classifier: Programming Language :: Python :: 3
Classifier: Programming Language :: Python :: 3.10
Classifier: Programming Language :: Python :: 3.11
Classifier: Programming Language :: Python :: 3.12
